htmlmaker/__init__.py
htmlmaker/htmlmaker.py
htmlmaker-0.0.7.dist-info/LICENSE
htmlmaker-0.0.7.dist-info/METADATA
htmlmaker-0.0.7.dist-info/WHEEL
htmlmaker-0.0.7.dist-info/top_level.txt
htmlmaker-0.0.7.dist-info/RECORD
