Metadata-Version: 2.1
Name: htmlmaker
Version: 0.0.7
Summary: Package for create html from data quickly.
Home-page: https://www.tsdm39.net
Author: tsdm
Author-email: tsdmtsdm@126.com
License: UNKNOWN
Platform: UNKNOWN
Classifier: Programming Language :: Python :: 3
Classifier: License :: OSI Approved :: MIT License
Classifier: Operating System :: OS Independent
License-File: LICENSE
